{
"type": "FeatureCollection",
"name": "arta",
"crs": { "type": "name", "properties": { "name": "urn:ogc:def:crs:OGC:1.3:CRS84" } },
"features": [
{ "type": "Feature", "properties": { "id": null, "rotate": 115 }, "geometry": { "type": "Point", "coordinates": [ 35.458082007758108, 47.08150286924738 ] } },
{ "type": "Feature", "properties": { "id": null, "rotate": 92 }, "geometry": { "type": "Point", "coordinates": [ 35.462437544393978, 47.094007758834955 ] } },
{ "type": "Feature", "properties": { "id": null, "rotate": 87 }, "geometry": { "type": "Point", "coordinates": [ 35.463163467166623, 47.092129741429375 ] } },
{ "type": "Feature", "properties": { "id": null, "rotate": 85 }, "geometry": { "type": "Point", "coordinates": [ 35.461058291125951, 47.099987320444228 ] } },
{ "type": "Feature", "properties": { "id": null, "rotate": 85 }, "geometry": { "type": "Point", "coordinates": [ 35.449153157654585, 47.098455430622494 ] } },
{ "type": "Feature", "properties": { "id": null, "rotate": 88 }, "geometry": { "type": "Point", "coordinates": [ 35.449298342209119, 47.096528151792192 ] } },
{ "type": "Feature", "properties": { "id": null, "rotate": 85 }, "geometry": { "type": "Point", "coordinates": [ 35.446104282009479, 47.092673384857527 ] } },
{ "type": "Feature", "properties": { "id": null, "rotate": 102 }, "geometry": { "type": "Point", "coordinates": [ 35.450605003199875, 47.089065465590025 ] } },
{ "type": "Feature", "properties": { "id": null, "rotate": 96 }, "geometry": { "type": "Point", "coordinates": [ 35.461421252512281, 47.087632114760531 ] } },
{ "type": "Feature", "properties": { "id": null, "rotate": 91 }, "geometry": { "type": "Point", "coordinates": [ 35.470713064002126, 47.104681547022864 ] } },
{ "type": "Feature", "properties": { "id": null, "rotate": 90 }, "geometry": { "type": "Point", "coordinates": [ 35.470350102615804, 47.106904983567482 ] } },
{ "type": "Feature", "properties": { "id": null, "rotate": 99 }, "geometry": { "type": "Point", "coordinates": [ 35.470640471724863, 47.112290256057143 ] } },
{ "type": "Feature", "properties": { "id": null, "rotate": 87 }, "geometry": { "type": "Point", "coordinates": [ 35.47477823152893, 47.110610504763265 ] } },
{ "type": "Feature", "properties": { "id": null, "rotate": 94 }, "geometry": { "type": "Point", "coordinates": [ 35.475504154301582, 47.112537273834754 ] } },
{ "type": "Feature", "properties": { "id": null, "rotate": 98 }, "geometry": { "type": "Point", "coordinates": [ 35.480440429155564, 47.11456277636406 ] } },
{ "type": "Feature", "properties": { "id": null, "rotate": 131 }, "geometry": { "type": "Point", "coordinates": [ 35.493289262231357, 47.150909903951536 ] } },
{ "type": "Feature", "properties": { "id": null, "rotate": 107 }, "geometry": { "type": "Point", "coordinates": [ 35.495539622826563, 47.153279505928658 ] } },
{ "type": "Feature", "properties": { "id": null, "rotate": 85 }, "geometry": { "type": "Point", "coordinates": [ 35.510421039665772, 47.156043908034732 ] } },
{ "type": "Feature", "properties": { "id": null, "rotate": 99 }, "geometry": { "type": "Point", "coordinates": [ 35.514341022638057, 47.159203048640023 ] } },
{ "type": "Feature", "properties": { "id": null, "rotate": 105 }, "geometry": { "type": "Point", "coordinates": [ 35.508098086793311, 47.153180774622342 ] } },
{ "type": "Feature", "properties": { "id": null, "rotate": 89 }, "geometry": { "type": "Point", "coordinates": [ 35.514921760856168, 47.160979982690101 ] } },
{ "type": "Feature", "properties": { "id": null, "rotate": 91 }, "geometry": { "type": "Point", "coordinates": [ 35.515429906797024, 47.16290492751402 ] } },
{ "type": "Feature", "properties": { "id": null, "rotate": 123 }, "geometry": { "type": "Point", "coordinates": [ 35.527915778486509, 47.189106852296653 ] } },
{ "type": "Feature", "properties": { "id": null, "rotate": 139 }, "geometry": { "type": "Point", "coordinates": [ 35.610308013181658, 47.265516867785273 ] } },
{ "type": "Feature", "properties": { "id": null, "rotate": null }, "geometry": { "type": "Point", "coordinates": [ 35.459170891917061, 47.401942093075604 ] } },
{ "type": "Feature", "properties": { "id": null, "rotate": null }, "geometry": { "type": "Point", "coordinates": [ 35.482110051532629, 47.395849105328601 ] } },
{ "type": "Feature", "properties": { "id": null, "rotate": null }, "geometry": { "type": "Point", "coordinates": [ 35.485304111732269, 47.395062862036895 ] } },
{ "type": "Feature", "properties": { "id": null, "rotate": 92 }, "geometry": { "type": "Point", "coordinates": [ 35.433691002597257, 47.31967651353537 ] } },
{ "type": "Feature", "properties": { "id": null, "rotate": 90 }, "geometry": { "type": "Point", "coordinates": [ 35.433255448933679, 47.317708043637673 ] } },
{ "type": "Feature", "properties": { "id": null, "rotate": 117 }, "geometry": { "type": "Point", "coordinates": [ 35.607985060309282, 47.26658582521835 ] } }
]
}
